<?xml version="1.0"?>
<movie><movieid>tt2084970</movieid><title>The Imitation Game</title><runtime>113 min</runtime><year>2014</year><mpaa>PG-13</mpaa><plot>Film over het levensverhaal van Alan Turing, een Britse wiskundige en informaticus. Tijdens de Tweede Wereldoorlog werkte hij voor de Britse crypto-analytische dienst, die als doel had onderschepte gecodeerde berichten van de Duitsers te ontcijferen. Turings grootste verwezelijking bestond erin om als &#xE9;&#xE9;n van de eersten de Duitse Enigma-codes te breken waardoor de Geallieerden de controle over de Atlantische Oceaan kregen en uiteindelijk de oorlog zouden winnen.</plot><genre>Drama,History,Thriller,War,Biography</genre></movie>
